brainnet_graph/__init__.py
brainnet_graph/construction.py
brainnet_graph/methods.py
brainnet_graph-0.2.2.dist-info/METADATA
brainnet_graph-0.2.2.dist-info/WHEEL
brainnet_graph-0.2.2.dist-info/entry_points.txt
brainnet_graph-0.2.2.dist-info/top_level.txt
brainnet_graph-0.2.2.dist-info/RECORD
